{"summaries":[{"symbol":{"__symbol":0,"members":[]},"metadata":{"NoDataState":"NoDataState","CannotChangeState":"CannotChangeState","EbillState":"EbillState","PostalState":"PostalState","InFlightToEbillState":"InFlightToEbillState","InFlightToPostalState":"InFlightToPostalState"}},{"symbol":{"__symbol":1,"members":[]},"metadata":{"Error":"error","Warning":"warning","Inform":"inform"}},{"symbol":{"__symbol":2,"members":[]},"metadata":{"__symbolic":"class","members":{"__ctor__":[{"__symbolic":"constructor","parameters":[null,null,null]}]}}},{"symbol":{"__symbol":3,"members":[]},"metadata":{"__symbolic":"class","members":{"__ctor__":[{"__symbolic":"constructor","parameters":[null,null,null,null,{"__symbol":4,"members":[]}]}],"beginTransition":[{"__symbolic":"method"}],"endTransition":[{"__symbolic":"method"}],"failTransition":[{"__symbolic":"method"}],"dump":[{"__symbolic":"method"}],"beginTransitionToEbill":[{"__symbolic":"method"}],"beginTransitionToPostal":[{"__symbolic":"method"}],"endTransitionToEbill":[{"__symbolic":"method"}],"endTransitionToPostal":[{"__symbolic":"method"}],"failedToTransitionToEbill":[{"__symbolic":"method"}],"failedToTransitionToPostal":[{"__symbolic":"method"}]}}}],"symbols":[{"__symbol":0,"name":"EmailBillingComponentState","filePath":"C:/AGL.Digital.Apps/src/app/myAccount/pages/settings/billing/emailBilling/emailBillingComponentModel.d.ts"},{"__symbol":1,"name":"AlertType","filePath":"C:/AGL.Digital.Apps/src/app/myAccount/pages/settings/billing/emailBilling/emailBillingComponentModel.d.ts"},{"__symbol":2,"name":"AlertMessage","filePath":"C:/AGL.Digital.Apps/src/app/myAccount/pages/settings/billing/emailBilling/emailBillingComponentModel.d.ts"},{"__symbol":3,"name":"EmailBillingComponentModel","filePath":"C:/AGL.Digital.Apps/src/app/myAccount/pages/settings/billing/emailBilling/emailBillingComponentModel.d.ts"},{"__symbol":4,"name":"BillDeliveryMethodType","filePath":"C:/AGL.Digital.Apps/src/app/myAccount/services/settings/model/index.d.ts"}]}