[
    {
        "account": "7019079511",
        "contract": "9400307029",
        "costs": [
            {
                "value": 4.07439,
                "startDateTime": "2016-01-01T00:00:00",
                "endDateTime": "2016-01-31T00:00:00",
                "estimatedRead": false
            },
            {
                "value": 26.531666,
                "startDateTime": "2016-02-01T00:00:00",
                "endDateTime": "2016-02-29T00:00:00",
                "estimatedRead": false
            },
            {
                "value": 31.625604,
                "startDateTime": "2016-03-01T00:00:00",
                "endDateTime": "2016-03-31T00:00:00",
                "estimatedRead": false
            },
            {
                "value": 37.0115,
                "startDateTime": "2016-04-01T00:00:00",
                "endDateTime": "2016-04-30T00:00:00",
                "estimatedRead": false
            },
            {
                "value": 32.708396,
                "startDateTime": "2016-05-01T00:00:00",
                "endDateTime": "2016-05-31T00:00:00",
                "estimatedRead": false
            },
            {
                "value": 55.216796,
                "startDateTime": "2016-06-01T00:00:00",
                "endDateTime": "2016-06-30T00:00:00",
                "estimatedRead": false
            },
            {
                "value": 60.072458,
                "startDateTime": "2016-07-01T00:00:00",
                "endDateTime": "2016-07-31T00:00:00",
                "estimatedRead": false
            },
            {
                "value": 49.307512,
                "startDateTime": "2016-08-01T00:00:00",
                "endDateTime": "2016-08-31T00:00:00",
                "estimatedRead": false
            },
            {
                "value": 46.076224,
                "startDateTime": "2016-09-01T00:00:00",
                "endDateTime": "2016-09-30T00:00:00",
                "estimatedRead": false
            },
            {
                "value": 44.820338,
                "startDateTime": "2016-10-01T00:00:00",
                "endDateTime": "2016-10-31T00:00:00",
                "estimatedRead": false
            },
            {
                "value": 33.816582,
                "startDateTime": "2016-11-01T00:00:00",
                "endDateTime": "2016-11-30T00:00:00",
                "estimatedRead": false
            },
            {
                "value": 43.358298,
                "startDateTime": "2016-12-01T00:00:00",
                "endDateTime": "2016-12-31T00:00:00",
                "estimatedRead": false
            },
            {
                "value": 64.903878,
                "startDateTime": "2017-01-01T00:00:00",
                "endDateTime": "2017-01-31T00:00:00",
                "estimatedRead": false
            },
            {
                "value": 42.937146,
                "startDateTime": "2017-02-01T00:00:00",
                "endDateTime": "2017-02-28T00:00:00",
                "estimatedRead": false
            }
        ],
        "consumption": [
            {
                "value": 26.428,
                "startDateTime": "2016-01-01T00:00:00",
                "endDateTime": "2016-01-31T00:00:00",
                "estimatedRead": false
            },
            {
                "value": 152.591,
                "startDateTime": "2016-02-01T00:00:00",
                "endDateTime": "2016-02-29T00:00:00",
                "estimatedRead": false
            },
            {
                "value": 171.08,
                "startDateTime": "2016-03-01T00:00:00",
                "endDateTime": "2016-03-31T00:00:00",
                "estimatedRead": false
            },
            {
                "value": 214.029,
                "startDateTime": "2016-04-01T00:00:00",
                "endDateTime": "2016-04-30T00:00:00",
                "estimatedRead": false
            },
            {
                "value": 186.592,
                "startDateTime": "2016-05-01T00:00:00",
                "endDateTime": "2016-05-31T00:00:00",
                "estimatedRead": false
            },
            {
                "value": 324.193,
                "startDateTime": "2016-06-01T00:00:00",
                "endDateTime": "2016-06-30T00:00:00",
                "estimatedRead": false
            },
            {
                "value": 362.383,
                "startDateTime": "2016-07-01T00:00:00",
                "endDateTime": "2016-07-31T00:00:00",
                "estimatedRead": false
            },
            {
                "value": 282.417,
                "startDateTime": "2016-08-01T00:00:00",
                "endDateTime": "2016-08-31T00:00:00",
                "estimatedRead": false
            },
            {
                "value": 255.215,
                "startDateTime": "2016-09-01T00:00:00",
                "endDateTime": "2016-09-30T00:00:00",
                "estimatedRead": false
            },
            {
                "value": 262.671,
                "startDateTime": "2016-10-01T00:00:00",
                "endDateTime": "2016-10-31T00:00:00",
                "estimatedRead": false
            },
            {
                "value": 193.634,
                "startDateTime": "2016-11-01T00:00:00",
                "endDateTime": "2016-11-30T00:00:00",
                "estimatedRead": false
            },
            {
                "value": 219.077,
                "startDateTime": "2016-12-01T00:00:00",
                "endDateTime": "2016-12-31T00:00:00",
                "estimatedRead": false
            },
            {
                "value": 274.615,
                "startDateTime": "2017-01-01T00:00:00",
                "endDateTime": "2017-01-31T00:00:00",
                "estimatedRead": false
            },
            {
                "value": 183.959,
                "startDateTime": "2017-02-01T00:00:00",
                "endDateTime": "2017-02-28T00:00:00",
                "estimatedRead": false
            }
        ],
        "hasNoBill": false
    }
]